myfr24/__init__.py
myfr24/exceptions.py
myfr24/myfr24.py
myfr24/network.py
myfr24/scraper.py
myfr24-0.1.1.dist-info/WHEEL
myfr24-0.1.1.dist-info/METADATA
myfr24-0.1.1.dist-info/RECORD
