Metadata-Version: 2.1
Name: myfr24
Version: 0.1.1
Summary: Simple tool to query myFlightRadar24 profiles
License: MIT
Author: Franco Correa
Author-email: franco@francocorrea.com
Requires-Python: >=3.10,<4.0
Classifier: License :: OSI Approved :: MIT License
Classifier: Programming Language :: Python :: 3
Classifier: Programming Language :: Python :: 3.10
Classifier: Programming Language :: Python :: 3.11
Requires-Dist: beautifulsoup4 (>=4.11.2,<5.0.0)
Requires-Dist: requests (>=2.28.2,<3.0.0)
